[{"videoId":"iHPRUCDHsns","commentId":"Ugx7h1POGwOyLRi-1Wt4AaABAg","author":"@ronnyfigueroa6310","text":"Que lindo perrito","likeCount":0,"publishedAt":"2025-09-17T03:12:08Z","parentId":null},{"videoId":"iHPRUCDHsns","commentId":"UgzLEUacy01FcACSajZ4AaABAg","author":"@bryansimbana2730","text":"Que bonitos perritos ❤","likeCount":0,"publishedAt":"2025-09-17T02:39:46Z","parentId":null},{"videoId":"iHPRUCDHsns","commentId":"Ugxoiqi71loOX0ydrz94AaABAg","author":"@DenissePerez-pz8cy","text":"Hermoso cachorro","likeCount":0,"publishedAt":"2025-09-17T01:20:56Z","parentId":null},{"videoId":"iHPRUCDHsns","commentId":"UgwmwZzbUDHkxaepedd4AaABAg","author":"@damianchamorro7953","text":"Yo tengo rottweiler igual","likeCount":0,"publishedAt":"2025-09-17T01:18:28Z","parentId":null},{"videoId":"iHPRUCDHsns","commentId":"Ugyp1om0wgcvqNvrK8B4AaABAg","author":"@Valee_772","text":"Lindo el Perro :)","likeCount":0,"publishedAt":"2025-09-17T01:02:02Z","parentId":null},{"videoId":"iHPRUCDHsns","commentId":"UgwtwCiP7e-hLmRo9pF4AaABAg","author":"@joanguanoona1040","text":"Que lindos y bellos perritos 😊❤","likeCount":0,"publishedAt":"2025-09-17T00:57:02Z","parentId":null},{"videoId":"iHPRUCDHsns","commentId":"UgxPLgn6wu17yqLUu3B4AaABAg","author":"@leonelcastillo-y5x","text":"😢😢😢😢","likeCount":0,"publishedAt":"2025-09-17T00:50:51Z","parentId":null},{"videoId":"iHPRUCDHsns","commentId":"UgzbOiXSwGuwvf-QdUl4AaABAg","author":"@MateoQuintanilla-p6j","text":"Que lindos perritos","likeCount":0,"publishedAt":"2025-09-17T00:50:08Z","parentId":null},{"videoId":"iHPRUCDHsns","commentId":"Ugz2LItLJTfqLhld8xp4AaABAg","author":"@androy8950","text":"Igiviñik🥵","likeCount":0,"publishedAt":"2025-09-17T00:42:53Z","parentId":null},{"videoId":"iHPRUCDHsns","commentId":"Ugysa8I1nGWuLtOBygd4AaABAg","author":"@PEPITO_CRACK-o4j","text":"Re bonito los perritos 💗","likeCount":0,"publishedAt":"2025-09-17T00:41:35Z","parentId":null},{"videoId":"iHPRUCDHsns","commentId":"UgwQFZW7jDJ_hh_YR-x4AaABAg","author":"@alejandratumailli5740","text":"Es un amor de perritos❤","likeCount":0,"publishedAt":"2025-09-17T00:41:06Z","parentId":null},{"videoId":"iHPRUCDHsns","commentId":"Ugz1VbXugfLbgrp-Xbx4AaABAg","author":"@JhonnStiven","text":"Que lindos perritos","likeCount":0,"publishedAt":"2025-09-17T00:40:48Z","parentId":null},{"videoId":"iHPRUCDHsns","commentId":"Ugx156TG30xvvKf81kV4AaABAg","author":"@Jean_antho","text":"💟💟","likeCount":0,"publishedAt":"2025-09-17T00:38:28Z","parentId":null},{"videoId":"iHPRUCDHsns","commentId":"UgxcnyByIATlSQAhn9R4AaABAg","author":"@torrespincayaxeljoel5787","text":"Hermoso ❤","likeCount":0,"publishedAt":"2025-09-17T00:14:13Z","parentId":null},{"videoId":"iHPRUCDHsns","commentId":"Ugz2OoJWAKksOHG0VJh4AaABAg","author":"@fernandaochog3186","text":"Que lindo el Geremias ❤😢","likeCount":0,"publishedAt":"2025-09-17T00:09:55Z","parentId":null},{"videoId":"iHPRUCDHsns","commentId":"Ugz9TIULrfqNt3Zs8gR4AaABAg","author":"@fernandaochog3186","text":"❤","likeCount":0,"publishedAt":"2025-09-17T00:09:07Z","parentId":null},{"videoId":"iHPRUCDHsns","commentId":"UgxNHc1lPGyGx51bL8p4AaABAg","author":"@jordancatota750","text":"Aguante el balu 😎","likeCount":0,"publishedAt":"2025-09-17T00:08:14Z","parentId":null},{"videoId":"iHPRUCDHsns","commentId":"UgwTB-Qs_3Fi0CmcEah4AaABAg","author":"@joelmullo8541","text":"que bonitooos","likeCount":0,"publishedAt":"2025-09-17T00:05:03Z","parentId":null},{"videoId":"iHPRUCDHsns","commentId":"UgysvGbVOw1Rd9fFFmB4AaABAg","author":"@isabelsalas1266","text":"Pequeños bonitos💝","likeCount":0,"publishedAt":"2025-09-16T23:55:42Z","parentId":null},{"videoId":"iHPRUCDHsns","commentId":"Ugx4kxsATGJjQOm950t4AaABAg","author":"@isabelsalas1266","text":"Que bonitoooos","likeCount":0,"publishedAt":"2025-09-16T23:55:12Z","parentId":null},{"videoId":"iHPRUCDHsns","commentId":"UgyFPEMaV3f87dKdTf14AaABAg","author":"@stevengalvez4937","text":"El perro del David","likeCount":0,"publishedAt":"2025-09-16T23:54:33Z","parentId":null},{"videoId":"iHPRUCDHsns","commentId":"UgxEmSOVw_pLCpVyLMl4AaABAg","author":"@stevengalvez4937","text":"Owwww","likeCount":0,"publishedAt":"2025-09-16T23:54:23Z","parentId":null},{"videoId":"iHPRUCDHsns","commentId":"UgyVcgx9Xk5l8kx7PqN4AaABAg","author":"@stevengalvez4937","text":"❤","likeCount":0,"publishedAt":"2025-09-16T23:54:18Z","parentId":null},{"videoId":"iHPRUCDHsns","commentId":"UgyI_hljztDf0ocoapN4AaABAg","author":"@matiascortez1706","text":"Wooow bonito perrito 🥹🥹","likeCount":0,"publishedAt":"2025-09-16T23:52:50Z","parentId":null},{"videoId":"iHPRUCDHsns","commentId":"UgxwOpyVtRkXwreTdWF4AaABAg","author":"@emiliochog3331","text":"Y las caras del Jeremías","likeCount":0,"publishedAt":"2025-09-16T23:48:35Z","parentId":null},{"videoId":"iHPRUCDHsns","commentId":"UgwPaGoGOerpLtgW_8J4AaABAg","author":"@emiliochog3331","text":"Bien bonito el balu","likeCount":0,"publishedAt":"2025-09-16T23:48:11Z","parentId":null},{"videoId":"iHPRUCDHsns","commentId":"UgzzByH8A4743YHgtpB4AaABAg","author":"@juanroman7298","text":"Mas contenido como este por favor 🙏","likeCount":1,"publishedAt":"2025-09-16T23:47:50Z","parentId":null},{"videoId":"iHPRUCDHsns","commentId":"Ugy-pRoLmlwEhGoemn94AaABAg","author":"@juanroman7298","text":"El mejor video 🗣🗣🗣","likeCount":1,"publishedAt":"2025-09-16T23:47:37Z","parentId":null},{"videoId":"iHPRUCDHsns","commentId":"Ugw0rZmPKcRj2LzQ9L94AaABAg","author":"@MayraRoman-ug6pq","text":"Preciosos","likeCount":0,"publishedAt":"2025-09-16T23:46:51Z","parentId":null},{"videoId":"iHPRUCDHsns","commentId":"UgxUwKYutokhDN84Yb54AaABAg","author":"@MayraRoman-ug6pq","text":"Están bien gorditos y bonitos","likeCount":0,"publishedAt":"2025-09-16T23:46:34Z","parentId":null},{"videoId":"iHPRUCDHsns","commentId":"Ugy3IBGkbNmCSOG5ICZ4AaABAg","author":"@emiliochog3331","text":"Que lindos ❤","likeCount":0,"publishedAt":"2025-09-16T23:43:20Z","parentId":null},{"videoId":"iHPRUCDHsns","commentId":"UgwVtuQamMK0lwghfk94AaABAg","author":"@emiliochog3331","text":"🫶🏻🫶🏻🫶🏻","likeCount":1,"publishedAt":"2025-09-16T23:43:13Z","parentId":null},{"videoId":"iHPRUCDHsns","commentId":"Ugx8dF6NTj_7CksbJAx4AaABAg","author":"@lissettechicaiza2720","text":"Chikibeibis","likeCount":0,"publishedAt":"2025-09-16T23:35:01Z","parentId":null},{"videoId":"iHPRUCDHsns","commentId":"UgxrlYuXOWhT6TZej_t4AaABAg","author":"@lissettechicaiza2720","text":"Que lindos bebés","likeCount":0,"publishedAt":"2025-09-16T23:34:50Z","parentId":null}]